Workbook

Sheet Dashboard
A1: Controle de Estoque - Produtos de Limpeza
A3: Indicador | B3: Valor | D3: Como controlar compras e retiradas
A4: Total de produtos cadastrados | B4: =COUNTA(Estoque!$A$2:$A$121) | D4: Use a aba Movimentos para registrar cada compra ou retirada. O estoque atual e o alerta COMPRAR são atualizados automaticamente na aba Estoque. Na coluna Última Compra, pode preencher a data manualmente quando quiser.
A5: Produtos para comprar | B5: =COUNTIF(Estoque!$J$2:$J$121,"COMPRAR")
A6: Total de entradas | B6: =SUM(Estoque!$F$2:$F$121)
A7: Total de saídas | B7: =SUM(Estoque!$G$2:$G$121)
A8: Gasto total em compras | B8: =SUM(Movimentos!$H$2:$H$121)
A11: Resumo por categoria | D11: Como ver a lista de compras
A12: Categoria | B12: Produtos | C12: Para comprar | D12: Na aba Estoque, filtre a coluna Comprar? e selecione COMPRAR. Assim aparecem todos os produtos abaixo ou iguais ao estoque mínimo. O número total de itens para comprar aparece no indicador “Produtos para comprar”.
A13: Desinfetante | B13: =COUNTIF(Estoque!$C$2:$C$121,A13) | C13: =COUNTIFS(Estoque!$C$2:$C$121,A13,Estoque!$J$2:$J$121,"COMPRAR")
A14: Detergente | B14: =COUNTIF(Estoque!$C$2:$C$121,A14) | C14: =COUNTIFS(Estoque!$C$2:$C$121,A14,Estoque!$J$2:$J$121,"COMPRAR")
A15: Desengordurante | B15: =COUNTIF(Estoque!$C$2:$C$121,A15) | C15: =COUNTIFS(Estoque!$C$2:$C$121,A15,Estoque!$J$2:$J$121,"COMPRAR")
A16: Álcool | B16: =COUNTIF(Estoque!$C$2:$C$121,A16) | C16: =COUNTIFS(Estoque!$C$2:$C$121,A16,Estoque!$J$2:$J$121,"COMPRAR")
A17: Lava-roupas | B17: =COUNTIF(Estoque!$C$2:$C$121,A17) | C17: =COUNTIFS(Estoque!$C$2:$C$121,A17,Estoque!$J$2:$J$121,"COMPRAR")
A18: Amaciante | B18: =COUNTIF(Estoque!$C$2:$C$121,A18) | C18: =COUNTIFS(Estoque!$C$2:$C$121,A18,Estoque!$J$2:$J$121,"COMPRAR")
A19: Cloro/Água sanitária | B19: =COUNTIF(Estoque!$C$2:$C$121,A19) | C19: =COUNTIFS(Estoque!$C$2:$C$121,A19,Estoque!$J$2:$J$121,"COMPRAR")
A20: Multiuso | B20: =COUNTIF(Estoque!$C$2:$C$121,A20) | C20: =COUNTIFS(Estoque!$C$2:$C$121,A20,Estoque!$J$2:$J$121,"COMPRAR")
A21: Limpa-vidros | B21: =COUNTIF(Estoque!$C$2:$C$121,A21) | C21: =COUNTIFS(Estoque!$C$2:$C$121,A21,Estoque!$J$2:$J$121,"COMPRAR")
A22: Cera/Polidor | B22: =COUNTIF(Estoque!$C$2:$C$121,A22) | C22: =COUNTIFS(Estoque!$C$2:$C$121,A22,Estoque!$J$2:$J$121,"COMPRAR")
A23: Aromatizador | B23: =COUNTIF(Estoque!$C$2:$C$121,A23) | C23: =COUNTIFS(Estoque!$C$2:$C$121,A23,Estoque!$J$2:$J$121,"COMPRAR")
A24: Material descartável | B24: =COUNTIF(Estoque!$C$2:$C$121,A24) | C24: =COUNTIFS(Estoque!$C$2:$C$121,A24,Estoque!$J$2:$J$121,"COMPRAR")
... A29: Outros | B29: =COUNTIF(Estoque!$C$2:$C$121,A29) | C29: =COUNTIFS(Estoque!$C$2:$C$121,A29,Estoque!$J$2:$J$121,"COMPRAR")

Sheet Estoque
A1: Código | B1: Produto | C1: Categoria | D1: Unidade | E1: Estoque Inicial | F1: Entradas | G1: Saídas | H1: Estoque Atual | I1: Estoque Mínimo | J1: Comprar? | K1: Última Compra | L1: Observações
A2: LIMP-001 | B2: Água sanitária | C2: Cloro/Água sanitária | D2: L | E2: 2 | F2: 5 | G2: 0 | H2: 7 | I2: 1 | J2: OK | K2: 46171 | L2: Essencial para desinfecção | M2: =IF($J2="COMPRAR",COUNTIF($J$2:J2,"COMPRAR"),"") | N2: =IF($M2="","",$A2)
A3: LIMP-002 | B3: Desinfetante | C3: Desinfetante | D3: L | E3: 3 | F3: 0 | G3: 1 | H3: 2 | I3: 2 | J3: COMPRAR | M3: =IF($J3="COMPRAR",COUNTIF($J$2:J3,"COMPRAR"),"") | N3: =IF($M3="","",$A3)
A4: LIMP-003 | B4: Detergente neutro | C4: Detergente | D4: L | E4: 2 | F4: 0 | G4: 0 | H4: 2 | I4: 1 | J4: OK | M4: =IF($J4="COMPRAR",COUNTIF($J$2:J4,"COMPRAR"),"") | N4: =IF($M4="","",$A4)
A5: LIMP-004 | B5: Desengordurante | C5: Desengordurante | D5: L | E5: 1 | F5: 0 | G5: 0 | H5: 1 | I5: 1 | J5: COMPRAR | M5: =IF($J5="COMPRAR",COUNTIF($J$2:J5,"COMPRAR"),"") | N5: =IF($M5="","",$A5)
A6: LIMP-005 | B6: Álcool 70% | C6: Álcool | D6: L | E6: 2 | F6: 0 | G6: 0 | H6: 2 | I6: 1 | J6: OK | M6: =IF($J6="COMPRAR",COUNTIF($J$2:J6,"COMPRAR"),"") | N6: =IF($M6="","",$A6)
A7: LIMP-006 | B7: Limpa-vidros | C7: Limpa-vidros | D7: L | E7: 1 | F7: 10 | G7: 0 | H7: 11 | I7: 1 | J7: OK | K7: 46175.454 | M7: =IF($J7="COMPRAR",COUNTIF($J$2:J7,"COMPRAR"),"") | N7: =IF($M7="","",$A7)
A8: LIMP-007 | B8: Multiuso | C8: Multiuso | D8: L | E8: 2 | F8: 0 | G8: 0 | H8: 2 | I8: 1 | J8: OK | M8: =IF($J8="COMPRAR",COUNTIF($J$2:J8,"COMPRAR"),"") | N8: =IF($M8="","",$A8)
A9: LIMP-008 | B9: Sabão em pó | C9: Lava-roupas | D9: kg | E9: 1 | F9: 10 | G9: 0 | H9: 11 | I9: 1 | J9: OK | K9: 46175.454 | M9: =IF($J9="COMPRAR",COUNTIF($J$2:J9,"COMPRAR"),"") | N9: =IF($M9="","",$A9)
A10: LIMP-009 | B10: Sabão líquido | C10: Lava-roupas | D10: L | E10: 1 | F10: 0 | G10: 0 | H10: 1 | I10: 1 | J10: COMPRAR | M10: =IF($J10="COMPRAR",COUNTIF($J$2:J10,"COMPRAR"),"") | N10: =IF($M10="","",$A10)
A11: LIMP-010 | B11: Amaciante | C11: Amaciante | D11: L | E11: 1 | F11: 0 | G11: 0 | H11: 1 | I11: 1 | J11: COMPRAR | M11: =IF($J11="COMPRAR",COUNTIF($J$2:J11,"COMPRAR"),"") | N11: =IF($M11="","",$A11)
A12: LIMP-011 | B12: Removedor de manchas | C12: Outros | D12: un | E12: 1 | F12: 0 | G12: 0 | H12: 1 | I12: 1 | J12: COMPRAR | M12: =IF($J12="COMPRAR",COUNTIF($J$2:J12,"COMPRAR"),"") | N12: =IF($M12="","",$A12)
A13: LIMP-012 | B13: Cera líquida | C13: Cera/Polidor | D13: L | E13: 1 | F13: 0 | G13: 0 | H13: 1 | I13: 1 | J13: COMPRAR | M13: =IF($J13="COMPRAR",COUNTIF($J$2:J13,"COMPRAR"),"") | N13: =IF($M13="","",$A13)
A14: LIMP-013 | B14: Polidor de móveis | C14: Cera/Polidor | D14: un | E14: 1 | F14: 0 | G14: 0 | H14: 1 | I14: 1 | J14: COMPRAR | M14: =IF($J14="COMPRAR",COUNTIF($J$2:J14,"COMPRAR"),"") | N14: =IF($M14="","",$A14)
A15: LIMP-014 | B15: Aromatizador de ambiente | C15: Aromatizador | D15: un | E15: 2 | F15: 0 | G15: 0 | H15: 2 | I15: 1 | J15: OK | M15: =IF($J15="COMPRAR",COUNTIF($J$2:J15,"COMPRAR"),"") | N15: =IF($M15="","",$A15)
A16: LIMP-015 | B16: Saco de lixo 30L | C16: Sacos de lixo | D16: rolo | E16: 2 | F16: 0 | G16: 0 | H16: 2 | I16: 1 | J16: OK | M16: =IF($J16="COMPRAR",COUNTIF($J$2:J16,"COMPRAR"),"") | N16: =IF($M16="","",$A16)
A17: LIMP-016 | B17: Saco de lixo 50L | C17: Sacos de lixo | D17: rolo | E17: 2 | F17: 0 | G17: 0 | H17: 2 | I17: 1 | J17: OK | M17: =IF($J17="COMPRAR",COUNTIF($J$2:J17,"COMPRAR"),"") | N17: =IF($M17="","",$A17)
A18: LIMP-017 | B18: Saco de lixo 100L | C18: Sacos de lixo | D18: rolo | E18: 1 | F18: 0 | G18: 0 | H18: 1 | I18: 1 | J18: COMPRAR | M18: =IF($J18="COMPRAR",COUNTIF($J$2:J18,"COMPRAR"),"") | N18: =IF($M18="","",$A18)
A19: LIMP-018 | B19: Papel toalha | C19: Material descartável | D19: rolo | E19: 4 | F19: 0 | G19: 0 | H19: 4 | I19: 2 | J19: OK | M19: =IF($J19="COMPRAR",COUNTIF($J$2:J19,"COMPRAR"),"") | N19: =IF($M19="","",$A19)
A20: LIMP-019 | B20: Papel higiénico | C20: Material descartável | D20: pacote | E20: 2 | F20: 0 | G20: 0 | H20: 2 | I20: 1 | J20: OK | M20: =IF($J20="COMPRAR",COUNTIF($J$2:J20,"COMPRAR"),"") | N20: =IF($M20="","",$A20)
A21: LIMP-020 | B21: Guardanapos | C21: Material descartável | D21: pacote | E21: 2 | F21: 0 | G21: 0 | H21: 2 | I21: 1 | J21: OK | M21: =IF($J21="COMPRAR",COUNTIF($J$2:J21,"COMPRAR"),"") | N21: =IF($M21="","",$A21)
... A41: LIMP-040 | B41: Limpa carpetes/estofados | C41: Outros | D41: un | E41: 1 | F41: 0 | G41: 0 | H41: 1 | I41: 1 | J41: COMPRAR | M41: =IF($J41="COMPRAR",COUNTIF($J$2:J41,"COMPRAR"),"") | N41: =IF($M41="","",$A41)
F42: =IF($A42="","",SUMIF(Movimentos!$J$2:$J$121,$A42&"|Compra",Movimentos!$E$2:$E$121)+SUMIF(Movimentos!$J$2:$J$121,$A42&"|Ajuste +",Movimentos!$E$2:$E$121)) | G42: =IF($A42="","",SUMIF(Movimentos!$J$2:$J$121,$A42&"|Retirada",Movimentos!$E$2:$E$121)+SUMIF(Movimentos!$J$2:$J$121,$A42&"|Ajuste -",Movimentos!$E$2:$E$121)) | H42: =IF($A42="","",$E42+$F42-$G42) | J42: =IF($A42="","",IF($H42<=$I42,"COMPRAR","OK")) | M42: =IF($J42="COMPRAR",COUNTIF($J$2:J42,"COMPRAR"),"") | N42: =IF($M42="","",$A42)
F43: =IF($A43="","",SUMIF(Movimentos!$J$2:$J$121,$A43&"|Compra",Movimentos!$E$2:$E$121)+SUMIF(Movimentos!$J$2:$J$121,$A43&"|Ajuste +",Movimentos!$E$2:$E$121)) | G43: =IF($A43="","",SUMIF(Movimentos!$J$2:$J$121,$A43&"|Retirada",Movimentos!$E$2:$E$121)+SUMIF(Movimentos!$J$2:$J$121,$A43&"|Ajuste -",Movimentos!$E$2:$E$121)) | H43: =IF($A43="","",$E43+$F43-$G43) | J43: =IF($A43="","",IF($H43<=$I43,"COMPRAR","OK")) | M43: =IF($J43="COMPRAR",COUNTIF($J$2:J43,"COMPRAR"),"") | N43: =IF($M43="","",$A43)
F44: =IF($A44="","",SUMIF(Movimentos!$J$2:$J$121,$A44&"|Compra",Movimentos!$E$2:$E$121)+SUMIF(Movimentos!$J$2:$J$121,$A44&"|Ajuste +",Movimentos!$E$2:$E$121)) | G44: =IF($A44="","",SUMIF(Movimentos!$J$2:$J$121,$A44&"|Retirada",Movimentos!$E$2:$E$121)+SUMIF(Movimentos!$J$2:$J$121,$A44&"|Ajuste -",Movimentos!$E$2:$E$121)) | H44: =IF($A44="","",$E44+$F44-$G44) | J44: =IF($A44="","",IF($H44<=$I44,"COMPRAR","OK")) | M44: =IF($J44="COMPRAR",COUNTIF($J$2:J44,"COMPRAR"),"") | N44: =IF($M44="","",$A44)
F45: =IF($A45="","",SUMIF(Movimentos!$J$2:$J$121,$A45&"|Compra",Movimentos!$E$2:$E$121)+SUMIF(Movimentos!$J$2:$J$121,$A45&"|Ajuste +",Movimentos!$E$2:$E$121)) | G45: =IF($A45="","",SUMIF(Movimentos!$J$2:$J$121,$A45&"|Retirada",Movimentos!$E$2:$E$121)+SUMIF(Movimentos!$J$2:$J$121,$A45&"|Ajuste -",Movimentos!$E$2:$E$121)) | H45: =IF($A45="","",$E45+$F45-$G45) | J45: =IF($A45="","",IF($H45<=$I45,"COMPRAR","OK")) | M45: =IF($J45="COMPRAR",COUNTIF($J$2:J45,"COMPRAR"),"") | N45: =IF($M45="","",$A45)
F46: =IF($A46="","",SUMIF(Movimentos!$J$2:$J$121,$A46&"|Compra",Movimentos!$E$2:$E$121)+SUMIF(Movimentos!$J$2:$J$121,$A46&"|Ajuste +",Movimentos!$E$2:$E$121)) | G46: =IF($A46="","",SUMIF(Movimentos!$J$2:$J$121,$A46&"|Retirada",Movimentos!$E$2:$E$121)+SUMIF(Movimentos!$J$2:$J$121,$A46&"|Ajuste -",Movimentos!$E$2:$E$121)) | H46: =IF($A46="","",$E46+$F46-$G46) | J46: =IF($A46="","",IF($H46<=$I46,"COMPRAR","OK")) | M46: =IF($J46="COMPRAR",COUNTIF($J$2:J46,"COMPRAR"),"") | N46: =IF($M46="","",$A46)
F47: =IF($A47="","",SUMIF(Movimentos!$J$2:$J$121,$A47&"|Compra",Movimentos!$E$2:$E$121)+SUMIF(Movimentos!$J$2:$J$121,$A47&"|Ajuste +",Movimentos!$E$2:$E$121)) | G47: =IF($A47="","",SUMIF(Movimentos!$J$2:$J$121,$A47&"|Retirada",Movimentos!$E$2:$E$121)+SUMIF(Movimentos!$J$2:$J$121,$A47&"|Ajuste -",Movimentos!$E$2:$E$121)) | H47: =IF($A47="","",$E47+$F47-$G47) | J47: =IF($A47="","",IF($H47<=$I47,"COMPRAR","OK")) | M47: =IF($J47="COMPRAR",COUNTIF($J$2:J47,"COMPRAR"),"") | N47: =IF($M47="","",$A47)
F48: =IF($A48="","",SUMIF(Movimentos!$J$2:$J$121,$A48&"|Compra",Movimentos!$E$2:$E$121)+SUMIF(Movimentos!$J$2:$J$121,$A48&"|Ajuste +",Movimentos!$E$2:$E$121)) | G48: =IF($A48="","",SUMIF(Movimentos!$J$2:$J$121,$A48&"|Retirada",Movimentos!$E$2:$E$121)+SUMIF(Movimentos!$J$2:$J$121,$A48&"|Ajuste -",Movimentos!$E$2:$E$121)) | H48: =IF($A48="","",$E48+$F48-$G48) | J48: =IF($A48="","",IF($H48<=$I48,"COMPRAR","OK")) | M48: =IF($J48="COMPRAR",COUNTIF($J$2:J48,"COMPRAR"),"") | N48: =IF($M48="","",$A48)
F49: =IF($A49="","",SUMIF(Movimentos!$J$2:$J$121,$A49&"|Compra",Movimentos!$E$2:$E$121)+SUMIF(Movimentos!$J$2:$J$121,$A49&"|Ajuste +",Movimentos!$E$2:$E$121)) | G49: =IF($A49="","",SUMIF(Movimentos!$J$2:$J$121,$A49&"|Retirada",Movimentos!$E$2:$E$121)+SUMIF(Movimentos!$J$2:$J$121,$A49&"|Ajuste -",Movimentos!$E$2:$E$121)) | H49: =IF($A49="","",$E49+$F49-$G49) | J49: =IF($A49="","",IF($H49<=$I49,"COMPRAR","OK")) | M49: =IF($J49="COMPRAR",COUNTIF($J$2:J49,"COMPRAR"),"") | N49: =IF($M49="","",$A49)
F50: =IF($A50="","",SUMIF(Movimentos!$J$2:$J$121,$A50&"|Compra",Movimentos!$E$2:$E$121)+SUMIF(Movimentos!$J$2:$J$121,$A50&"|Ajuste +",Movimentos!$E$2:$E$121)) | G50: =IF($A50="","",SUMIF(Movimentos!$J$2:$J$121,$A50&"|Retirada",Movimentos!$E$2:$E$121)+SUMIF(Movimentos!$J$2:$J$121,$A50&"|Ajuste -",Movimentos!$E$2:$E$121)) | H50: =IF($A50="","",$E50+$F50-$G50) | J50: =IF($A50="","",IF($H50<=$I50,"COMPRAR","OK")) | M50: =IF($J50="COMPRAR",COUNTIF($J$2:J50,"COMPRAR"),"") | N50: =IF($M50="","",$A50)
F51: =IF($A51="","",SUMIF(Movimentos!$J$2:$J$121,$A51&"|Compra",Movimentos!$E$2:$E$121)+SUMIF(Movimentos!$J$2:$J$121,$A51&"|Ajuste +",Movimentos!$E$2:$E$121)) | G51: =IF($A51="","",SUMIF(Movimentos!$J$2:$J$121,$A51&"|Retirada",Movimentos!$E$2:$E$121)+SUMIF(Movimentos!$J$2:$J$121,$A51&"|Ajuste -",Movimentos!$E$2:$E$121)) | H51: =IF($A51="","",$E51+$F51-$G51) | J51: =IF($A51="","",IF($H51<=$I51,"COMPRAR","OK")) | M51: =IF($J51="COMPRAR",COUNTIF($J$2:J51,"COMPRAR"),"") | N51: =IF($M51="","",$A51)
F52: =IF($A52="","",SUMIF(Movimentos!$J$2:$J$121,$A52&"|Compra",Movimentos!$E$2:$E$121)+SUMIF(Movimentos!$J$2:$J$121,$A52&"|Ajuste +",Movimentos!$E$2:$E$121)) | G52: =IF($A52="","",SUMIF(Movimentos!$J$2:$J$121,$A52&"|Retirada",Movimentos!$E$2:$E$121)+SUMIF(Movimentos!$J$2:$J$121,$A52&"|Ajuste -",Movimentos!$E$2:$E$121)) | H52: =IF($A52="","",$E52+$F52-$G52) | J52: =IF($A52="","",IF($H52<=$I52,"COMPRAR","OK")) | M52: =IF($J52="COMPRAR",COUNTIF($J$2:J52,"COMPRAR"),"") | N52: =IF($M52="","",$A52)
F53: =IF($A53="","",SUMIF(Movimentos!$J$2:$J$121,$A53&"|Compra",Movimentos!$E$2:$E$121)+SUMIF(Movimentos!$J$2:$J$121,$A53&"|Ajuste +",Movimentos!$E$2:$E$121)) | G53: =IF($A53="","",SUMIF(Movimentos!$J$2:$J$121,$A53&"|Retirada",Movimentos!$E$2:$E$121)+SUMIF(Movimentos!$J$2:$J$121,$A53&"|Ajuste -",Movimentos!$E$2:$E$121)) | H53: =IF($A53="","",$E53+$F53-$G53) | J53: =IF($A53="","",IF($H53<=$I53,"COMPRAR","OK")) | M53: =IF($J53="COMPRAR",COUNTIF($J$2:J53,"COMPRAR"),"") | N53: =IF($M53="","",$A53)
... F121: =IF($A121="","",SUMIF(Movimentos!$J$2:$J$121,$A121&"|Compra",Movimentos!$E$2:$E$121)+SUMIF(Movimentos!$J$2:$J$121,$A121&"|Ajuste +",Movimentos!$E$2:$E$121)) | G121: =IF($A121="","",SUMIF(Movimentos!$J$2:$J$121,$A121&"|Retirada",Movimentos!$E$2:$E$121)+SUMIF(Movimentos!$J$2:$J$121,$A121&"|Ajuste -",Movimentos!$E$2:$E$121)) | H121: =IF($A121="","",$E121+$F121-$G121) | J121: =IF($A121="","",IF($H121<=$I121,"COMPRAR","OK")) | M121: =IF($J121="COMPRAR",COUNTIF($J$2:J121,"COMPRAR"),"") | N121: =IF($M121="","",$A121)

Sheet Movimentos
A1: Data | B1: Código | C1: Produto | D1: Tipo | E1: Quantidade | F1: Responsável | G1: Preço Unit. | H1: Total Compra | I1: Observação | J1: Chave sistema
A2: 46171 | B2: LIMP-001 | C2: =IFERROR(VLOOKUP(B2,Estoque!$A$2:$B$121,2,FALSE),"") | D2: Compra | E2: 5 | F2: Rafael | G2: 1.5 | H2: =IF(D2="Compra",E2*G2,"") | I2: Exemplo: compra adiciona ao estoque | J2: =IF(B2="","",B2&"|"&D2)
A3: 46171 | B3: LIMP-002 | C3: =IFERROR(VLOOKUP(B3,Estoque!$A$2:$B$121,2,FALSE),"") | D3: Retirada | E3: 1 | F3: Rafael | H3: =IF(D3="Compra",E3*G3,"") | I3: Exemplo: retirada reduz o estoque | J3: =IF(B3="","",B3&"|"&D3)
C4: =IFERROR(VLOOKUP(B4,Estoque!$A$2:$B$121,2,FALSE),"") | H4: =IF(D4="Compra",E4*G4,"") | J4: =IF(B4="","",B4&"|"&D4)
C5: =IFERROR(VLOOKUP(B5,Estoque!$A$2:$B$121,2,FALSE),"") | H5: =IF(D5="Compra",E5*G5,"") | J5: =IF(B5="","",B5&"|"&D5)
C6: =IFERROR(VLOOKUP(B6,Estoque!$A$2:$B$121,2,FALSE),"") | H6: =IF(D6="Compra",E6*G6,"") | J6: =IF(B6="","",B6&"|"&D6)
C7: =IFERROR(VLOOKUP(B7,Estoque!$A$2:$B$121,2,FALSE),"") | H7: =IF(D7="Compra",E7*G7,"") | J7: =IF(B7="","",B7&"|"&D7)
C8: =IFERROR(VLOOKUP(B8,Estoque!$A$2:$B$121,2,FALSE),"") | H8: =IF(D8="Compra",E8*G8,"") | J8: =IF(B8="","",B8&"|"&D8)
C9: =IFERROR(VLOOKUP(B9,Estoque!$A$2:$B$121,2,FALSE),"") | H9: =IF(D9="Compra",E9*G9,"") | J9: =IF(B9="","",B9&"|"&D9)
C10: =IFERROR(VLOOKUP(B10,Estoque!$A$2:$B$121,2,FALSE),"") | H10: =IF(D10="Compra",E10*G10,"") | J10: =IF(B10="","",B10&"|"&D10)
C11: =IFERROR(VLOOKUP(B11,Estoque!$A$2:$B$121,2,FALSE),"") | H11: =IF(D11="Compra",E11*G11,"") | J11: =IF(B11="","",B11&"|"&D11)
C12: =IFERROR(VLOOKUP(B12,Estoque!$A$2:$B$121,2,FALSE),"") | H12: =IF(D12="Compra",E12*G12,"") | J12: =IF(B12="","",B12&"|"&D12)
C13: =IFERROR(VLOOKUP(B13,Estoque!$A$2:$B$121,2,FALSE),"") | H13: =IF(D13="Compra",E13*G13,"") | J13: =IF(B13="","",B13&"|"&D13)
C14: =IFERROR(VLOOKUP(B14,Estoque!$A$2:$B$121,2,FALSE),"") | H14: =IF(D14="Compra",E14*G14,"") | J14: =IF(B14="","",B14&"|"&D14)
C15: =IFERROR(VLOOKUP(B15,Estoque!$A$2:$B$121,2,FALSE),"") | H15: =IF(D15="Compra",E15*G15,"") | J15: =IF(B15="","",B15&"|"&D15)
... C121: =IFERROR(VLOOKUP(B121,Estoque!$A$2:$B$121,2,FALSE),"") | H121: =IF(D121="Compra",E121*G121,"") | J121: =IF(B121="","",B121&"|"&D121)
A201: 46175.454 | B201: LIMP-006 | C201: Limpa-vidros | D201: Compra | E201: 10 | F201: Luciana | G201: 1.2 | H201: 12 | I201: Movimento registrado pelo sistema | J201: LIMP-006|Compra
A202: 46175.454 | B202: LIMP-008 | C202: Sabão em pó | D202: Compra | E202: 10 | F202: Rafael | G202: 2 | H202: 20 | I202: Movimento registrado pelo sistema | J202: LIMP-008|Compra

Sheet Listas
A1: Categorias | C1: Unidades | E1: Tipos de movimento | G1: Responsáveis
A2: Desinfetante | C2: un | E2: Compra | G2: Rafael
A3: Detergente | C3: L | E3: Retirada | G3: Funcionário
A4: Desengordurante | C4: ml | E4: Ajuste + | G4: Cliente
A5: Álcool | C5: kg | E5: Ajuste - | G5: Outro
A6: Lava-roupas | C6: g
A7: Amaciante | C7: pacote
A8: Cloro/Água sanitária | C8: caixa
A9: Multiuso | C9: rolo
A10: Limpa-vidros | C10: par
A11: Cera/Polidor | C11: fardo
A12: Aromatizador
A13: Material descartável
A14: EPI
A15: Acessórios
A16: Panos/Esponjas
A17: Sacos de lixo
A18: Outros

Sheet Como usar
A1: Como usar a planilha
A3: Passo | B3: Ação | C3: Descrição
A4: 1 | B4: Cadastrar produtos | C4: Na aba Estoque, adicione produtos nas linhas em branco. Preencha Código, Produto, Categoria, Unidade, Estoque Inicial e Estoque Mínimo.
A5: 2 | B5: Registrar compras | C5: Na aba Movimentos, coloque a data, escolha o código, selecione Tipo = Compra e informe a quantidade. O estoque aumenta automaticamente.
A6: 3 | B6: Registrar retirada/uso | C6: Na aba Movimentos, escolha Tipo = Retirada e informe a quantidade usada. O estoque diminui automaticamente.
A7: 4 | B7: Corrigir contagem | C7: Use Ajuste + ou Ajuste - quando fizer uma contagem manual e precisar corrigir o saldo.
A8: 5 | B8: Ver o que falta comprar | C8: Veja a coluna Comprar? na aba Estoque ou a Lista rápida para comprar no Dashboard.
A9: 6 | B9: Não editar colunas automáticas | C9: Evite alterar as colunas Entradas, Saídas, Estoque Atual, Comprar?, Produto e Total Compra, pois elas têm fórmulas.
